qa_pytest_webdriver/__init__.py
qa_pytest_webdriver/selenium_configuration.py
qa_pytest_webdriver/selenium_steps.py
qa_pytest_webdriver/selenium_tests.py
qa_pytest_webdriver-0.1.1.dist-info/METADATA
qa_pytest_webdriver-0.1.1.dist-info/WHEEL
qa_pytest_webdriver-0.1.1.dist-info/RECORD
