Metadata-Version: 2.4
Name: qa_pytest_webdriver
Version: 0.1.1
Summary: PyTest WebDriver library
Author-email: Adrian Herscu <adrian.herscu@gmail.com>
Requires-Python: >=3.13
Requires-Dist: more-itertools
Requires-Dist: pyfunctional
Requires-Dist: pyhamcrest
Requires-Dist: pytest
Requires-Dist: qa-pytest-commons
Requires-Dist: qa-testing-utils
Requires-Dist: selenium
Requires-Dist: tenacity
Requires-Dist: webdriver-manager
